tests
tusharedeps
